decodess/__init__.py
decoss-0.0.1.dist-info/LICENCE.txt
decoss-0.0.1.dist-info/METADATA
decoss-0.0.1.dist-info/WHEEL
decoss-0.0.1.dist-info/top_level.txt
decoss-0.0.1.dist-info/RECORD
