Metadata-Version: 2.1
Name: decoss
Version: 0.0.1
Summary: Basic program package
Home-page: UNKNOWN
Author: Harsh Kumar
Author-email: harsh1717gupta@gmail.com
License: UNKNOWN
Platform: UNKNOWN
Classifier: Programming Language :: Python :: 3
Classifier: License :: OSI Approved :: MIT License
Classifier: Operating System :: OS Independent
License-File: LICENCE.txt
